todo_cli/__init__.py
todo_cli/all_todos.py
todo_cli/create.py
todo_cli/delete_todo_list.py
todo_cli/main.py
todo_cli/main_cfg.py
todo_cli/rename.py
todo_cli/todo_add.py
todo_cli/todo_delete.py
todo_cli/todo_get.py
todo_cli/todo_update.py
todo_cli_hpk-0.0.2.dist-info/METADATA
todo_cli_hpk-0.0.2.dist-info/WHEEL
todo_cli_hpk-0.0.2.dist-info/entry_points.txt
todo_cli_hpk-0.0.2.dist-info/licenses/LICENSE
todo_cli_hpk-0.0.2.dist-info/RECORD
