Metadata-Version: 2.4
Name: todo-cli-hpk
Version: 0.0.2
Summary: A simple ToDo CLI app using Click and SQLite
Project-URL: Homepage, https://github.com/hosseinpk/ToDo_CLI
Project-URL: Issues, https://github.com/hosseinpk/ToDo_CLI/issues
Author-email: Hossein Pakaein <hosseinpakaein@gmail.com>
License: MIT License
License-File: LICENSE
Keywords: cli,click,productivity,sqlite,todo
Classifier: Development Status :: 5 - Production/Stable
Classifier: Environment :: Console
Classifier: Intended Audience :: End Users/Desktop
Classifier: License :: OSI Approved :: MIT License
Classifier: Programming Language :: Python
Classifier: Programming Language :: Python :: 3
Classifier: Programming Language :: Python :: 3.11
Classifier: Topic :: Utilities
Requires-Python: >=3.11
Requires-Dist: click>=8.1.7
